hub/__main__.py
pop_cli/config.yaml
pop_cli/plugin/cli.py
pop_cli/plugin/completer.py
pop_cli/plugin/config.py
pop_cli/plugin/console.py
pop_cli/plugin/init.py
pop_cli/plugin/legacy.py
pop_cli/plugin/ref.py
pop_cli/plugin/state.py
pop_cli-7.0.1.dist-info/METADATA
pop_cli-7.0.1.dist-info/WHEEL
pop_cli-7.0.1.dist-info/entry_points.txt
pop_cli-7.0.1.dist-info/RECORD
