Metadata-Version: 2.3
Name: pop-cli
Version: 7.0.1
Summary: A POP cli interface
Author-email: Tyler Levy Conde <yonstib@gmail.com>
Classifier: Development Status :: 5 - Production/Stable
Classifier: License :: OSI Approved :: Apache Software License
Classifier: Operating System :: OS Independent
Classifier: Programming Language :: Python :: 3.10
Classifier: Programming Language :: Python :: 3.11
Classifier: Programming Language :: Python :: 3.12
Requires-Python: >=3.10
Requires-Dist: aioconsole
Requires-Dist: aiopath
Requires-Dist: cpop>=36.0.1
Requires-Dist: prompt-toolkit
Provides-Extra: test
Requires-Dist: cpop[test]; extra == 'test'
Requires-Dist: pexpect; extra == 'test'
Requires-Dist: pytest; extra == 'test'
Requires-Dist: pytest-asyncio; extra == 'test'
